[{"label":"unary op:Cos, dtype:F32, pipeline:UnaryFromBufferContiguous","mean":0.000011264,"min":0.000011264,"max":0.000011264,"std":0.0,"count":1,"m_type":"Duration"},{"label":"unary op:Cos, dtype:F32, pipeline:UnaryFromBufferContiguous","mean":6144.0,"min":6144.0,"max":6144.0,"std":0.0,"count":1,"m_type":"OutputSize"},{"label":"unary op:Cos, dtype:F32, pipeline:UnaryFromBufferContiguous","mean":96.0,"min":96.0,"max":96.0,"std":0.0,"count":1,"m_type":"DispatchSize"},{"label":"binary op:Add, dtype:F32, pipeline:BinaryBufferFromBufferContiguousBoth","mean":8.902572549019607e-6,"min":7.168e-6,"max":0.00036864,"std":9.679511170692046e-6,"count":6120,"m_type":"Duration"},{"label":"binary op:Add, dtype:F32, pipeline:BinaryBufferFromBufferContiguousBoth","mean":216.0,"min":144.0,"max":288.0,"std":72.0,"count":6120,"m_type":"OutputSize"},{"label":"binary op:Add, dtype:F32, pipeline:BinaryBufferFromBufferContiguousBoth","mean":4.0,"min":3.0,"max":5.0,"std":1.0,"count":6120,"m_type":"DispatchSize"},{"label":"binary op:Div, dtype:F32, pipeline:BinaryBufferFromBuffer","mean":0.000011334551181102362,"min":9.216e-6,"max":0.00034304,"std":0.000010343012179004906,"count":1524,"m_type":"Duration"},{"label":"binary op:Div, dtype:F32, pipeline:BinaryBufferFromBuffer","mean":771.0,"min":12.0,"max":1530.0,"std":439.9374955604489,"count":1524,"m_type":"OutputSize"},{"label":"binary op:Div, dtype:F32, pipeline:BinaryBufferFromBuffer","mean":12.531496062992126,"min":1.0,"max":24.0,"std":6.873218604283439,"count":1524,"m_type":"DispatchSize"},{"label":"unary op:Exp, dtype:F32, pipeline:UnaryFromBufferContiguous","mean":8.986781699346405e-6,"min":7.168e-6,"max":0.000280576,"std":7.350948355566224e-6,"count":3060,"m_type":"Duration"},{"label":"unary op:Exp, dtype:F32, pipeline:UnaryFromBufferContiguous","mean":768.0,"min":6.0,"max":1530.0,"std":312.3075407350902,"count":3060,"m_type":"OutputSize"},{"label":"unary op:Exp, dtype:F32, pipeline:UnaryFromBufferContiguous","mean":12.24313725490196,"min":1.0,"max":24.0,"std":4.883315126859929,"count":3060,"m_type":"DispatchSize"},{"label":"unary op:Sin, dtype:F32, pipeline:UnaryFromBufferContiguous","mean":0.000010208,"min":0.000010208,"max":0.000010208,"std":0.0,"count":1,"m_type":"Duration"},{"label":"unary op:Sin, dtype:F32, pipeline:UnaryFromBufferContiguous","mean":6144.0,"min":6144.0,"max":6144.0,"std":0.0,"count":1,"m_type":"OutputSize"},{"label":"unary op:Sin, dtype:F32, pipeline:UnaryFromBufferContiguous","mean":96.0,"min":96.0,"max":96.0,"std":0.0,"count":1,"m_type":"DispatchSize"},{"label":"binary op:Div, dtype:F32, pipeline:BinaryBufferFromBufferContiguousBoth","mean":8.499979166666666e-6,"min":7.168e-6,"max":0.000018432,"std":9.856125842503356e-7,"count":1536,"m_type":"Duration"},{"label":"binary op:Div, dtype:F32, pipeline:BinaryBufferFromBufferContiguousBoth","mean":765.0234375,"min":6.0,"max":768.0,"std":47.53189140654508,"count":1536,"m_type":"OutputSize"},{"label":"binary op:Div, dtype:F32, pipeline:BinaryBufferFromBufferContiguousBoth","mean":11.95703125,"min":1.0,"max":12.0,"std":0.686155912692908,"count":1536,"m_type":"DispatchSize"},{"label":"binary op:Minus, dtype:F32, pipeline:BinaryBufferFromBufferContiguousBoth","mean":8.773479452054795e-6,"min":7.168e-6,"max":0.00026112,"std":6.228376083043811e-6,"count":3066,"m_type":"Duration"},{"label":"binary op:Minus, dtype:F32, pipeline:BinaryBufferFromBufferContiguousBoth","mean":143.72994129158513,"min":6.0,"max":144.0,"std":6.098784309619388,"count":3066,"m_type":"OutputSize"},{"label":"binary op:Minus, dtype:F32, pipeline:BinaryBufferFromBufferContiguousBoth","mean":2.996086105675147,"min":1.0,"max":3.0,"std":0.08838817840027724,"count":3066,"m_type":"DispatchSize"},{"label":"unary op:Affine, dtype:F32, pipeline:UnaryFromBufferContiguous","mean":9.519508496732026e-6,"min":8.192e-6,"max":0.000300032,"std":7.82644918353659e-6,"count":3060,"m_type":"Duration"},{"label":"unary op:Affine, dtype:F32, pipeline:UnaryFromBufferContiguous","mean":768.0,"min":6.0,"max":1530.0,"std":312.3075407350902,"count":3060,"m_type":"OutputSize"},{"label":"unary op:Affine, dtype:F32, pipeline:UnaryFromBufferContiguous","mean":12.24313725490196,"min":1.0,"max":24.0,"std":4.883315126859929,"count":3060,"m_type":"DispatchSize"},{"label":"copy strided dtype:F32","mean":0.000012306183727034121,"min":9.216e-6,"max":0.000156672,"std":2.9762711363391652e-6,"count":3048,"m_type":"Duration"},{"label":"copy strided dtype:F32","mean":37008.0,"min":576.0,"max":73440.0,"std":21116.999786901546,"count":3048,"m_type":"OutputSize"},{"label":"copy strided dtype:F32","mean":578.5,"min":9.0,"max":1148.0,"std":329.9549211634826,"count":3048,"m_type":"DispatchSize"},{"label":"u32_to_f32","mean":9.216e-6,"min":9.216e-6,"max":9.216e-6,"std":0.0,"count":1,"m_type":"Duration"},{"label":"u32_to_f32","mean":256.0,"min":256.0,"max":256.0,"std":0.0,"count":1,"m_type":"OutputSize"},{"label":"u32_to_f32","mean":4.0,"min":4.0,"max":4.0,"std":0.0,"count":1,"m_type":"DispatchSize"},{"label":"rms_norm, dtype:F32","mean":0.000011361612066365007,"min":0.00001024,"max":0.000304128,"std":5.1807667726578e-6,"count":3315,"m_type":"Duration"},{"label":"rms_norm, dtype:F32","mean":288.0,"min":288.0,"max":288.0,"std":0.0,"count":3315,"m_type":"OutputSize"},{"label":"rms_norm, dtype:F32","mean":1.0,"min":1.0,"max":1.0,"std":0.0,"count":3315,"m_type":"DispatchSize"},{"label":"binary op:Mult, dtype:F32, pipeline:BinaryBufferFromBuffer","mean":0.00001408224836601307,"min":0.000011264,"max":0.000364544,"std":0.000011140182542526074,"count":12240,"m_type":"Duration"},{"label":"binary op:Mult, dtype:F32, pipeline:BinaryBufferFromBuffer","mean":144.0,"min":144.0,"max":144.0,"std":0.0,"count":12240,"m_type":"OutputSize"},{"label":"binary op:Mult, dtype:F32, pipeline:BinaryBufferFromBuffer","mean":3.0,"min":3.0,"max":3.0,"std":0.0,"count":12240,"m_type":"DispatchSize"},{"label":"reduce op:Sum, dtype:F32","mean":0.000011375749019607843,"min":0.00001024,"max":0.000314368,"std":7.800510901301516e-6,"count":1530,"m_type":"Duration"},{"label":"reduce op:Sum, dtype:F32","mean":768.0,"min":6.0,"max":1530.0,"std":441.66955973895233,"count":1530,"m_type":"OutputSize"},{"label":"reduce op:Sum, dtype:F32","mean":6.0,"min":6.0,"max":6.0,"std":0.0,"count":1530,"m_type":"DispatchSize"},{"label":"unary op:Neg, dtype:F32, pipeline:UnaryFromBufferContiguous","mean":9.274875816993464e-6,"min":7.168e-6,"max":0.000356352,"std":0.000012793958515883644,"count":1530,"m_type":"Duration"},{"label":"unary op:Neg, dtype:F32, pipeline:UnaryFromBufferContiguous","mean":768.0,"min":768.0,"max":768.0,"std":0.0,"count":1530,"m_type":"OutputSize"},{"label":"unary op:Neg, dtype:F32, pipeline:UnaryFromBufferContiguous","mean":12.0,"min":12.0,"max":12.0,"std":0.0,"count":1530,"m_type":"DispatchSize"},{"label":"binary op:Mult, dtype:F32, pipeline:BinaryBufferFromBufferContiguousBoth","mean":8.49520522875817e-6,"min":7.168e-6,"max":0.00028672,"std":7.165267899317645e-6,"count":1530,"m_type":"Duration"},{"label":"binary op:Mult, dtype:F32, pipeline:BinaryBufferFromBufferContiguousBoth","mean":768.0,"min":768.0,"max":768.0,"std":0.0,"count":1530,"m_type":"OutputSize"},{"label":"binary op:Mult, dtype:F32, pipeline:BinaryBufferFromBufferContiguousBoth","mean":12.0,"min":12.0,"max":12.0,"std":0.0,"count":1530,"m_type":"DispatchSize"},{"label":"index_select : dtypeF32","mean":0.000010613333333333334,"min":9.216e-6,"max":0.000016384,"std":9.829837783487222e-7,"count":255,"m_type":"Duration"},{"label":"index_select : dtypeF32","mean":288.0,"min":288.0,"max":288.0,"std":0.0,"count":255,"m_type":"OutputSize"},{"label":"index_select : dtypeF32","mean":36.0,"min":36.0,"max":36.0,"std":0.0,"count":255,"m_type":"DispatchSize"},{"label":"copy2d dtype:F32","mean":0.000010394161100196464,"min":7.168e-6,"max":0.000393216,"std":0.000010607501902208883,"count":12216,"m_type":"Duration"},{"label":"copy2d dtype:F32","mean":9305.96463654224,"min":144.0,"max":73152.0,"std":19003.166731208206,"count":12216,"m_type":"OutputSize"},{"label":"copy2d dtype:F32","mean":1163.24557956778,"min":18.0,"max":9144.0,"std":2375.395841401026,"count":12216,"m_type":"DispatchSize"},{"label":"reduce op:Max, dtype:F32","mean":0.000011723126797385621,"min":0.00001024,"max":0.000301056,"std":0.000011586666042594711,"count":1530,"m_type":"Duration"},{"label":"reduce op:Max, dtype:F32","mean":768.0,"min":6.0,"max":1530.0,"std":441.66955973895233,"count":1530,"m_type":"OutputSize"},{"label":"reduce op:Max, dtype:F32","mean":6.0,"min":6.0,"max":6.0,"std":0.0,"count":1530,"m_type":"DispatchSize"},{"label":"binary op:Minus, dtype:F32, pipeline:BinaryBufferFromBuffer","mean":0.000011363422572178476,"min":9.216e-6,"max":0.000324608,"std":9.947417383997828e-6,"count":1524,"m_type":"Duration"},{"label":"binary op:Minus, dtype:F32, pipeline:BinaryBufferFromBuffer","mean":771.0,"min":12.0,"max":1530.0,"std":439.9374955604489,"count":1524,"m_type":"OutputSize"},{"label":"binary op:Minus, dtype:F32, pipeline:BinaryBufferFromBuffer","mean":12.531496062992126,"min":1.0,"max":24.0,"std":6.873218604283439,"count":1524,"m_type":"DispatchSize"},{"label":"matmul, dtype:F32","mean":0.000029261221160701555,"min":9.216e-6,"max":0.000653312,"std":0.000040829333842937234,"count":14026,"m_type":"Duration"},{"label":"matmul, dtype:F32","mean":277466.03621845145,"min":48.0,"max":9216000.0,"std":1219094.5764648954,"count":14026,"m_type":"OutputSize"},{"label":"matmul, dtype:F32","mean":64.16027377727079,"min":6.0,"max":2000.0,"std":263.97917309692264,"count":14026,"m_type":"DispatchSize"}]